_roffio/__init__.py
_roffio/endianess_handler.py
_roffio/lazy_tuple.py
_roffio/parser.py
_roffio/reading.py
_roffio/writing.py
_roffio/tokenizer/__init__.py
_roffio/tokenizer/abstract_roff_body_tokenizer.py
_roffio/tokenizer/binary_roff_body_tokenizer.py
_roffio/tokenizer/combinators.py
_roffio/tokenizer/common.py
_roffio/tokenizer/errors.py
_roffio/tokenizer/roff_tokenizer.py
_roffio/tokenizer/text_roff_body_tokenizer.py
_roffio/tokenizer/token.py
_roffio/tokenizer/token_kind.py
roffio/__init__.py
roffio/version.py
roffio-1.1.1.dist-info/licenses/LICENSE.md
roffio-1.1.1.dist-info/METADATA
roffio-1.1.1.dist-info/WHEEL
roffio-1.1.1.dist-info/top_level.txt
roffio-1.1.1.dist-info/RECORD
