Metadata-Version: 2.4
Name: RoffIO
Version: 1.1.1
Summary: A (lazy) parser and writer for the Roxar Open File Format (ROFF).
Home-page: https://github.com/equinor/roffio
Author: Equinor
Author-email: fg_sib-scout@equinor.com
License: LGPL-3.0
Platform: any
Classifier: Development Status :: 1 - Planning
Classifier: License :: OSI Approved :: GNU Lesser General Public License v3 or later (LGPLv3+)
Classifier: Programming Language :: Python
Classifier: Programming Language :: Python :: 3.8
Classifier: Programming Language :: Python :: 3.9
Classifier: Programming Language :: Python :: 3.10
Classifier: Programming Language :: Python :: 3.11
Classifier: Programming Language :: Python :: 3.12
License-File: LICENSE.md
Requires-Dist: dataclasses>=0.6; python_version < "3.7"
Requires-Dist: numpy
Dynamic: author
Dynamic: author-email
Dynamic: classifier
Dynamic: description
Dynamic: description-content-type
Dynamic: home-page
Dynamic: license
Dynamic: license-file
Dynamic: platform
Dynamic: requires-dist
Dynamic: summary
